pygenlib/__init__.py
pygenlib/create_library_template.py
pygenlib/templates/readme_template.md
pygenlib/templates/setup_template.py
pygenlib/templates/updater_template.py
pygenlib-0.0.12.dist-info/METADATA
pygenlib-0.0.12.dist-info/WHEEL
pygenlib-0.0.12.dist-info/entry_points.txt
pygenlib-0.0.12.dist-info/top_level.txt
pygenlib-0.0.12.dist-info/RECORD
