Metadata-Version: 2.1
Name: pygenlib
Version: 0.0.12
Summary: A Python library for generating other Python libraries
Author: Your Name
Author-email: your.email@example.com
Classifier: License :: OSI Approved :: MIT License
Classifier: Programming Language :: Python :: 3
Classifier: Operating System :: OS Independent
Classifier: Intended Audience :: Developers
